volute/__init__.py
volute/colors.py
volute/datastructures.py
volute/py.typed
volute/render.py
volute-1.0.1.dist-info/LICENSE
volute-1.0.1.dist-info/METADATA
volute-1.0.1.dist-info/WHEEL
volute-1.0.1.dist-info/top_level.txt
volute-1.0.1.dist-info/RECORD
