Metadata-Version: 2.1
Name: volute
Version: 1.0.1
Summary: A Python library for rendering heatmaps to Web Mercator tiles
Home-page: https://github.com/saintamh/volute
Author: Hervé Saint-Amand
Classifier: License :: OSI Approved :: MIT License
Classifier: Operating System :: OS Independent
Classifier: Programming Language :: Python :: 3
License-File: LICENSE
Requires-Dist: haversine~=2.0
Requires-Dist: mercantile~=1.0
Requires-Dist: numpy~=1.13
Requires-Dist: Pillow~=9.0
